taiga_cfd/__init__.py
taiga_cfd/cfd_visualizer.py
taiga_cfd/cli.py
taiga_cfd/taiga_cfd_generator.py
taiga_cfd_analytics-2.3.3.data/data/share/taiga-cfd-analytics/CHANGELOG.md
taiga_cfd_analytics-2.3.3.data/data/share/taiga-cfd-analytics/CONTRIBUTING.md
taiga_cfd_analytics-2.3.3.data/data/share/taiga-cfd-analytics/LICENSE
taiga_cfd_analytics-2.3.3.data/data/share/taiga-cfd-analytics/README.md
taiga_cfd_analytics-2.3.3.dist-info/licenses/LICENSE
taiga_cfd_analytics-2.3.3.dist-info/METADATA
taiga_cfd_analytics-2.3.3.dist-info/WHEEL
taiga_cfd_analytics-2.3.3.dist-info/entry_points.txt
taiga_cfd_analytics-2.3.3.dist-info/top_level.txt
taiga_cfd_analytics-2.3.3.dist-info/RECORD
