Metadata-Version: 2.4
Name: taiga-cfd-analytics
Version: 2.3.3
Summary: Enterprise-grade CFD analytics system for Taiga with modern TUI
Home-page: https://github.com/ydrgzm/taiga-cfd-analytics
Author: Muhammad Zeshan Ayub
Author-email: Muhammad Zeshan Ayub <zeshanayub.connect@gmail.com>
Maintainer-email: Muhammad Zeshan Ayub <zeshanayub.connect@gmail.com>
License: MIT License
Project-URL: Homepage, https://github.com/ydrgzm/taiga-cfd-analytics
Project-URL: Documentation, https://github.com/ydrgzm/taiga-cfd-analytics#readme
Project-URL: Repository, https://github.com/ydrgzm/taiga-cfd-analytics.git
Project-URL: Bug Tracker, https://github.com/ydrgzm/taiga-cfd-analytics/issues
Project-URL: Discussions, https://github.com/ydrgzm/taiga-cfd-analytics/discussions
Project-URL: Changelog, https://github.com/ydrgzm/taiga-cfd-analytics/blob/main/CHANGELOG.md
Project-URL: Funding, https://github.com/sponsors/ydrgzm
Keywords: taiga,cfd,cumulative-flow-diagram,analytics,project-management,kanban,agile,visualization,reporting,enterprise,tui,terminal,dashboard,metrics,scrum,devops
Classifier: Development Status :: 5 - Production/Stable
Classifier: Intended Audience :: Developers
Classifier: Intended Audience :: Information Technology
Classifier: Intended Audience :: System Administrators
Classifier: Topic :: Software Development :: Libraries :: Python Modules
Classifier: Topic :: Office/Business :: Financial :: Spreadsheet
Classifier: Topic :: Scientific/Engineering :: Visualization
Classifier: Topic :: Scientific/Engineering :: Information Analysis
Classifier: License :: OSI Approved :: MIT License
Classifier: Programming Language :: Python :: 3
Classifier: Programming Language :: Python :: 3.8
Classifier: Programming Language :: Python :: 3.9
Classifier: Programming Language :: Python :: 3.10
Classifier: Programming Language :: Python :: 3.11
Classifier: Programming Language :: Python :: 3.12
Classifier: Operating System :: OS Independent
Classifier: Operating System :: MacOS
Classifier: Operating System :: Microsoft :: Windows
Classifier: Operating System :: POSIX :: Linux
Classifier: Environment :: Console
Classifier: Environment :: Console :: Curses
Classifier: Natural Language :: English
Requires-Python: >=3.8
License-File: LICENSE
Requires-Dist: requests>=2.25.1
Requires-Dist: matplotlib>=3.5.0
Requires-Dist: seaborn>=0.11.0
Requires-Dist: pandas>=1.3.0
Requires-Dist: numpy>=1.21.0
Requires-Dist: rich>=13.0.0
Requires-Dist: textual>=0.44.0
Provides-Extra: dev
Requires-Dist: pytest>=7.0.0; extra == "dev"
Requires-Dist: black>=22.0.0; extra == "dev"
Requires-Dist: flake8>=4.0.0; extra == "dev"
Requires-Dist: mypy>=0.950; extra == "dev"
Requires-Dist: build>=0.8.0; extra == "dev"
Requires-Dist: twine>=4.0.0; extra == "dev"
Provides-Extra: docs
Requires-Dist: sphinx>=4.0.0; extra == "docs"
Requires-Dist: sphinx-rtd-theme>=1.0.0; extra == "docs"
Dynamic: author
Dynamic: home-page
Dynamic: license-file
Dynamic: requires-python
